LICENSE
MANIFEST.in
README.md
setup.py
blipleo/__init__.py
blipleo/__version__.py
blipleo/charts.py
blipleo/colors.py
blipleo/leo.py
blipleo/leocsv.py
blipleo/models.py
blipleo.egg-info/PKG-INFO
blipleo.egg-info/SOURCES.txt
blipleo.egg-info/dependency_links.txt
blipleo.egg-info/requires.txt
blipleo.egg-info/top_level.txt
blipleo/templates/LICENSE
blipleo/templates/leo_page1.svg
blipleo/templates/leo_page2.svg
blipleo/templates/leo_page3.svg