Metadata-Version: 2.1
Name: blipleo
Version: 0.1a5.post1
Summary: Language Experience Overview (LEO) Report Generator
Home-page: https://blipntu.github.io/LEO/
Author: Le Tuan Anh
Author-email: tuananh.le@ntu.edu.sg
License: GNU General Public License v3 (GPLv3)
Project-URL: Bug Tracker, https://github.com/BLIPNTU/LEO/issues
Project-URL: Source Code, https://github.com/BLIPNTU/LEO/
Keywords: nlp
Platform: any
Classifier: Programming Language :: Python :: 3
Classifier: Programming Language :: Python :: 3.6
Classifier: Programming Language :: Python :: 3.7
Classifier: Programming Language :: Python :: 3.8
Classifier: Programming Language :: Python :: 3.9
Classifier: Programming Language :: Python :: 3.10
Classifier: Programming Language :: Python :: 3.11
Classifier: Development Status :: 3 - Alpha
Classifier: Natural Language :: English
Classifier: Environment :: Plugins
Classifier: Intended Audience :: Developers
Classifier: License :: OSI Approved :: GNU General Public License v3 (GPLv3)
Classifier: Operating System :: OS Independent
Classifier: Topic :: Multimedia :: Graphics
Classifier: Topic :: Multimedia :: Graphics :: Editors :: Vector-Based
Classifier: Topic :: Software Development :: Libraries :: Python Modules
License-File: LICENSE
